ping_ws/__init__.py
ping_ws/ping_ws.py
websocket_ping-1.0.1.dist-info/LICENSE
websocket_ping-1.0.1.dist-info/METADATA
websocket_ping-1.0.1.dist-info/WHEEL
websocket_ping-1.0.1.dist-info/top_level.txt
websocket_ping-1.0.1.dist-info/RECORD
