Metadata-Version: 2.1
Name: websocket_ping
Version: 1.0.1
Summary: Small package to connect to and then send ping message to a websocket endpoint.  Used for a quick test of ws servers.
Home-page: UNKNOWN
Author: willm
Author-email: will@loblollysoftware.com
License: UNKNOWN
Platform: UNKNOWN
Classifier: Programming Language :: Python :: 3
Classifier: License :: OSI Approved :: MIT License
Classifier: Operating System :: OS Independent
Requires-Python: >=3.8
License-File: LICENSE
